prefetch_parser/__init__.py
prefetch_parser/prefetch_parser.py
prefetch_parser-1.0.0.dist-info/WHEEL
prefetch_parser-1.0.0.dist-info/LICENSE
prefetch_parser-1.0.0.dist-info/METADATA
prefetch_parser-1.0.0.dist-info/RECORD
