Metadata-Version: 2.1
Name: prefetch-parser
Version: 1.0.0
Summary: 
Home-page: https://github.com/DavidCruciani/prefetch_parser
License: BSD-2-Clause
Keywords: prefetch
Author: David Cruciani
Author-email: david.cruciani@circl.lu
Requires-Python: >=3.8,<4.0
Classifier: License :: OSI Approved :: BSD License
Classifier: Programming Language :: Python :: 3
Classifier: Programming Language :: Python :: 3.8
Classifier: Programming Language :: Python :: 3.9
Classifier: Programming Language :: Python :: 3.10
Classifier: Programming Language :: Python :: 3.11
Requires-Dist: libscca-python (>=20221027,<20221028)
Project-URL: Repository, https://github.com/DavidCruciani/prefetch_parser
